__main__.py
module1.py
test_unique_1032024-0.0.1.dist-info/METADATA
test_unique_1032024-0.0.1.dist-info/WHEEL
test_unique_1032024-0.0.1.dist-info/top_level.txt
test_unique_1032024-0.0.1.dist-info/RECORD
